fineforms/__init__.py
fineforms/wrappers.py
fineforms/locale/de/LC_MESSAGES/django.mo
fineforms/locale/de/LC_MESSAGES/django.po
fineforms/locale/rm/LC_MESSAGES/django.mo
fineforms/locale/rm/LC_MESSAGES/django.po
fineforms/packages/__init__.py
fineforms/packages/foundation_xy_grid/__init__.py
fineforms/packages/foundation_xy_grid/templates/fineforms/errors.html
fineforms/packages/foundation_xy_grid/templates/fineforms/field.html
fineforms/packages/foundation_xy_grid/templates/fineforms/submit.html
fineforms/templates/fineforms/errors.html
fineforms/templates/fineforms/field-plain.html
fineforms/templates/fineforms/field.html
fineforms/templates/fineforms/fields.html
fineforms/templates/fineforms/submit.html
fineforms/templatetags/__init__.py
fineforms/templatetags/fineforms.py
django_fineforms-0.7.0.dist-info/LICENSE
django_fineforms-0.7.0.dist-info/METADATA
django_fineforms-0.7.0.dist-info/WHEEL
django_fineforms-0.7.0.dist-info/top_level.txt
django_fineforms-0.7.0.dist-info/RECORD
