Metadata-Version: 2.1
Name: django-fineforms
Version: 0.7.0
Summary: Form rendering for Django
Home-page: http://github.com/matthiask/django-fineforms/
Author: Matthias Kestenholz
Author-email: mk@feinheit.ch
License: BSD-3-Clause
Platform: OS Independent
Classifier: Environment :: Web Environment
Classifier: Framework :: Django
Classifier: Intended Audience :: Developers
Classifier: License :: OSI Approved :: BSD License
Classifier: Operating System :: OS Independent
Classifier: Programming Language :: Python
Classifier: Programming Language :: Python :: 3
Classifier: Programming Language :: Python :: 3 :: Only
Classifier: Programming Language :: Python :: 3.8
Classifier: Programming Language :: Python :: 3.9
Classifier: Programming Language :: Python :: 3.10
Classifier: Programming Language :: Python :: Implementation :: CPython
Classifier: Topic :: Internet :: WWW/HTTP :: Dynamic Content
Classifier: Topic :: Software Development
Classifier: Topic :: Software Development :: Libraries :: Application Frameworks
Requires-Python: >=3.8
License-File: LICENSE
Requires-Dist: Django (>=3.2)
Provides-Extra: tests
Requires-Dist: coverage ; extra == 'tests'
